S/__init__.py
S/mysql_connector_python-9.3.0.dist-info/1/__init__.py
S/mysql_connector_python-9.3.0.dist-info/1/auth_client.py
S/mysql_connector_python-9.3.0.dist-info/1/auth_staff.py
S/mysql_connector_python-9.3.0.dist-info/1/db.py
S/mysql_connector_python-9.3.0.dist-info/1/main.py
S/mysql_connector_python-9.3.0.dist-info/1/requirements.txt
S/mysql_connector_python-9.3.0.dist-info/1/screens_admin.py
S/mysql_connector_python-9.3.0.dist-info/1/screens_client.py
S/mysql_connector_python-9.3.0.dist-info/1/screens_manager.py
S/mysql_connector_python-9.3.0.dist-info/1/screens_staff.py
S/mysql_connector_python-9.3.0.dist-info/licenses/LICENSE.txt
S/mysql_connector_python-9.3.0.dist-info/INSTALLER
S/mysql_connector_python-9.3.0.dist-info/METADATA
S/mysql_connector_python-9.3.0.dist-info/RECORD
S/mysql_connector_python-9.3.0.dist-info/REQUESTED
S/mysql_connector_python-9.3.0.dist-info/WHEEL
S/mysql_connector_python-9.3.0.dist-info/top_level.txt
antonshagin-0.1.4.dist-info/METADATA
antonshagin-0.1.4.dist-info/WHEEL
antonshagin-0.1.4.dist-info/top_level.txt
antonshagin-0.1.4.dist-info/RECORD
